simplebase/__init__.py
simplebase/simplebase.py
simplebase-0.0.4.dist-info/METADATA
simplebase-0.0.4.dist-info/WHEEL
simplebase-0.0.4.dist-info/licenses/LICENSE
simplebase-0.0.4.dist-info/RECORD
