Metadata-Version: 2.1
Name: simplebase
Version: 0.0.4
Summary: A simple package for usage of Firebase for novice Python users
Author-email: sneaky <24535asssci@gmail.com>
License-File: LICENSE
Classifier: License :: OSI Approved :: MIT License
Classifier: Operating System :: OS Independent
Classifier: Programming Language :: Python :: 3
Requires-Python: >=3.1
Requires-Dist: firebase-admin>=6.2.0
